{
  "_format": "hh-sol-cache-1",
  "files": {
    "/Users/stefan/signor-did-contracts/contracts/DIDRegistry.sol": {
      "lastModificationDate": 1605542942910,
      "sourceName": "contracts/DIDRegistry.sol",
      "solcConfig": {
        "version": "0.7.3",
        "settings": {
          "optimizer": {
            "enabled": false,
            "runs": 200
          },
          "outputSelection": {
            "*": {
              "*": [
                "abi",
                "evm.bytecode",
                "evm.deployedBytecode",
                "evm.methodIdentifiers"
              ],
              "": [
                "ast"
              ]
            }
          }
        }
      },
      "imports": [],
      "versionPragmas": [
        "^0.7.0"
      ],
      "artifacts": [
        "DIDRegistry"
      ]
    }
  }
}
